vtap/__init__.py
vtap/__main__.py
vtap/ascii.py
vtap/components/__init__.py
vtap/components/ascii_picture.py
vtap/components/ascii_video.py
vtap/components/audio_player.py
vtap/components/demo_setup.py
vtap/components/downloader.py
vtap/core/__init__.py
vtap/core/ascii_art.py
vtap/core/close_handling.py
vtap/core/loading_bar.py
vtap/core/logger.py
vtap/core/my_args.py
vtap/core/signal_handling.py
vtap-0.0.6.dist-info/METADATA
vtap-0.0.6.dist-info/WHEEL
vtap-0.0.6.dist-info/entry_points.txt
vtap-0.0.6.dist-info/top_level.txt
vtap-0.0.6.dist-info/RECORD
