Metadata-Version: 2.1
Name: vtap
Version: 0.0.6
Summary: Download and play YouTube videos as synchronized ASCII art with audio in your terminal using multithreading for smooth playback.
Home-page: https://github.com/VinnyVanGogh/vtap.git
Author: VinnyVanGogh
Author-email: VinnyVanGogh <computerscience@vinny-van-gogh.com>
License: MIT
Project-URL: Homepage, https://github.com/VinnyVanGogh/vtap.git
Requires-Python: >=3.10
Requires-Dist: certifi==2024.8.30
Requires-Dist: charset-normalizer==3.3.2
Requires-Dist: cipher==0.1
Requires-Dist: colorama==0.4.6
Requires-Dist: idna==3.10
Requires-Dist: imageio==2.35.1
Requires-Dist: imageio-ffmpeg==0.5.1
Requires-Dist: numpy==2.1.1
Requires-Dist: opencv-python==4.10.0.84
Requires-Dist: pillow==10.4.0
Requires-Dist: protobuf==4.24.4
Requires-Dist: pytube2==15.0.10
Requires-Dist: requests==2.32.3
Requires-Dist: setuptools==75.1.0
Requires-Dist: urllib3==2.2.3
Requires-Dist: wheel~=0.44.0
